[
  {
    "href": "/news/",
    "imageSrc": "/images/news/",
    "title": "Atrapada sensacional de Dani Sierra",
    "text": "Dani Sierra ha realizado una jugada sensacional en el jardin central para salvar a su equipo 2 carreras vitales"
  },
  {
    "href": "/news/",
    "imageSrc": "/images/news/summer-cup-2024.jpg",
    "title": "6 innings en blanco para Rafa Parra",
    "text": "Rafa Parra ha estado intratable en su primera actuación con los Layetanos, propinando 6 arepas a los Blue Socks"
  }
]
